setup.cfg
setup.py
bustime/__init__.py
bustime/__main__.py
bustime/monitor.py
bustime.egg-info/PKG-INFO
bustime.egg-info/SOURCES.txt
bustime.egg-info/dependency_links.txt
bustime.egg-info/requires.txt
bustime.egg-info/top_level.txt