Metadata-Version: 1.1
Name: bustime
Version: 0.2.1
Summary: SDK for the MTA Bus Time API
Home-page: https://github.com/celeryclub/bustime
Author: Steve Davis
Author-email: steve@celery.club
License: UNKNOWN
Download-URL: https://github.com/celeryclub/bustime/tarball/0.2.1
Keywords: mta bustime
Platform: UNKNOWN
